pixeon/__init__.py
pixeon/accuracy_tools.py
pixeon-0.0.1.dist-info/License.txt
pixeon-0.0.1.dist-info/METADATA
pixeon-0.0.1.dist-info/WHEEL
pixeon-0.0.1.dist-info/top_level.txt
pixeon-0.0.1.dist-info/RECORD
