Metadata-Version: 2.1
Name: pixeon
Version: 0.0.1
Summary: very powerful image recognition tool
Home-page: https://github.com/Loganius-II/Pixeon
Author: Logan McDermott
Author-email: 1loganmcd@gmail.com
License: MIT
Classifier: Programming Language :: Python :: 3
Classifier: License :: OSI Approved :: MIT License
Classifier: Operating System :: OS Independent
Requires-Python: >=3.8
License-File: License.txt
